btdx/DX.py
btdx/__init__.py
btdx-0.0.3.dist-info/LICENSE
btdx-0.0.3.dist-info/METADATA
btdx-0.0.3.dist-info/WHEEL
btdx-0.0.3.dist-info/top_level.txt
btdx-0.0.3.dist-info/RECORD
