Metadata-Version: 2.1
Name: btdx
Version: 0.0.3
Summary: Designed to interact with the Milton Keynes' BT DX platform
Author-email: Shobhit Maniar <shobhitmaniar10@gmail.com>
Project-URL: Homepage, https://github.com/ShobhitManiar/data-exchange
Project-URL: Issues, https://github.com/ShobhitManiar/data-exchange/issues
Classifier: Development Status :: 1 - Planning
Classifier: Programming Language :: Python :: 3
Classifier: Programming Language :: Python :: 3.8
Classifier: Programming Language :: Python :: 3.9
Classifier: Programming Language :: Python :: 3.10
Classifier: Programming Language :: Python :: 3.11
Classifier: Programming Language :: Python :: 3.12
Classifier: License :: OSI Approved :: MIT License
Classifier: Operating System :: OS Independent
Classifier: Intended Audience :: Developers
Classifier: Topic :: Database :: Database Engines/Servers
Classifier: Topic :: Scientific/Engineering :: Information Analysis
Classifier: Topic :: Software Development
Classifier: Typing :: Typed
Requires-Python: >=3.8
License-File: LICENSE
Requires-Dist: requests
